fastpaip/__init__.py
fastpaip-0.0.1.dist-info/licenses/LICENSE
fastpaip-0.0.1.dist-info/METADATA
fastpaip-0.0.1.dist-info/WHEEL
fastpaip-0.0.1.dist-info/top_level.txt
fastpaip-0.0.1.dist-info/RECORD
